whatsapp_bridge/__init__.py
whatsapp_bridge/bot.py
whatsapp_bridge/exceptions.py
whatsapp_bridge/listener.py
whatsapp_bridge/api/__init__.py
whatsapp_bridge/api/client.py
whatsapp_bridge/bot_module/__init__.py
whatsapp_bridge/bot_module/application.py
whatsapp_bridge/bot_module/context.py
whatsapp_bridge/bot_module/filters.py
whatsapp_bridge/bot_module/handlers.py
whatsapp_bridge/bot_module/update.py
whatsapp_bridge/bridge/__init__.py
whatsapp_bridge/bridge/manager.py
whatsapp_bridge/bridge/manager_module/__init__.py
whatsapp_bridge/bridge/manager_module/bridge_manager.py
whatsapp_bridge/bridge/manager_module/output_handler.py
whatsapp_bridge/bridge/manager_module/process_management.py
whatsapp_bridge/bridge/manager_module/stream_handler.py
whatsapp_bridge/config/__init__.py
whatsapp_bridge/config/settings.py
whatsapp_bridge/config/setup.py
whatsapp_bridge/core/__init__.py
whatsapp_bridge/core/client.py
whatsapp_bridge/core/connection.py
whatsapp_bridge/core/client_module/__init__.py
whatsapp_bridge/core/client_module/media_handler.py
whatsapp_bridge/core/client_module/message_handler.py
whatsapp_bridge/core/client_module/messaging.py
whatsapp_bridge/core/client_module/whatsapp_client.py
whatsapp_bridge/core/connection_module/__init__.py
whatsapp_bridge/core/connection_module/connection_manager.py
whatsapp_bridge/core/connection_module/setup.py
whatsapp_bridge/db/__init__.py
whatsapp_bridge/db/reader.py
whatsapp_bridge/listener_module/__init__.py
whatsapp_bridge/listener_module/message_listener.py
whatsapp_bridge/state/manager.py
whatsapp_bridge/utils/__init__.py
whatsapp_bridge/utils/commands.py
whatsapp_bridge/utils/db_reader.py
whatsapp_bridge-0.1.0.dist-info/licenses/LICENSE.md
whatsapp_bridge-0.1.0.dist-info/METADATA
whatsapp_bridge-0.1.0.dist-info/WHEEL
whatsapp_bridge-0.1.0.dist-info/top_level.txt
whatsapp_bridge-0.1.0.dist-info/RECORD
