Metadata-Version: 2.4
Name: whatsapp-bridge
Version: 0.1.0
Summary: A Python library for interacting with WhatsApp Reverse API, enabling personal message sending, receiving, and media handling.
Author: DevsDoCode
License: MPL-2.0
Project-URL: Homepage, https://github.com/Devs-Do-Code/whatsapp-bridge
Project-URL: Repository, https://github.com/Devs-Do-Code/whatsapp-bridge
Project-URL: YouTube, https://www.youtube.com/@DevsDoCode
Project-URL: Instagram, https://www.instagram.com/sree.shades_/
Project-URL: Twitter, https://x.com/Anand_Sreejan
Project-URL: Telegram, https://t.me/devsdocode
Project-URL: Discord, https://discord.com/invite/4gGcqsWWde
Project-URL: LinkedIn, https://www.linkedin.com/in/developer-sreejan/
Project-URL: GitHub, https://github.com/SreejanPersonal
Keywords: whatsapp-bridge,whatsapp,api,reverse-engineering,messaging,bot
Classifier: Development Status :: 3 - Alpha
Classifier: Intended Audience :: Developers
Classifier: License :: OSI Approved :: Mozilla Public License 2.0 (MPL 2.0)
Classifier: Programming Language :: Python :: 3
Classifier: Programming Language :: Python :: 3.8
Classifier: Programming Language :: Python :: 3.9
Classifier: Programming Language :: Python :: 3.10
Classifier: Programming Language :: Python :: 3.11
Classifier: Operating System :: OS Independent
Classifier: Topic :: Communications :: Chat
Requires-Python: >=3.8
License-File: LICENSE.md
Requires-Dist: requests>=2.25.0
Dynamic: license-file
